bioprov/__init__.py
bioprov/bioprov
bioprov/bioprov.py
bioprov/utils.py
bioprov/data/__init__.py
bioprov/data/blastdb/megares_blastdb.nhr
bioprov/data/blastdb/megares_blastdb.nin
bioprov/data/blastdb/megares_blastdb.nog
bioprov/data/blastdb/megares_blastdb.nsd
bioprov/data/blastdb/megares_blastdb.nsi
bioprov/data/blastdb/megares_blastdb.nsq
bioprov/data/blastdb/megares_subset.fna
bioprov/data/datasets/genome_annotation_input.tsv
bioprov/data/datasets/picocyano.csv
bioprov/data/genomes/GCF_000007925.1_ASM792v1_genomic.fna
bioprov/data/genomes/GCF_000010065.1_ASM1006v1_genomic.fna
bioprov/data/genomes/GCF_000011485.1_ASM1148v1_genomic.fna
bioprov/data/genomes/GCF_000012625.1_ASM1262v1_genomic.fna
bioprov/data/genomes/GCF_000316515.1_ASM31651v1_genomic.fna
bioprov/programs/__init__.py
bioprov/programs/programs.py
bioprov/src/__init__.py
bioprov/src/config.py
bioprov/src/files.py
bioprov/src/main.py
bioprov/src/prov.py
bioprov/src/workflow.py
bioprov/tests/__init__.py
bioprov/tests/test_bioprov_imports.py
bioprov/tests/test_bioprov_integration.py
bioprov/tests/test_bioprov_programs.py
bioprov/tests/test_bioprov_workflows.py
bioprov/tests/test_src_config.py
bioprov/tests/test_src_file.py
bioprov/tests/test_src_main.py
bioprov/tests/test_src_prov.py
bioprov/workflows/__init__.py
bioprov/workflows/workflows.py
bioprov-0.1.24.data/scripts/bioprov
bioprov-0.1.24.dist-info/LICENSE
bioprov-0.1.24.dist-info/METADATA
bioprov-0.1.24.dist-info/WHEEL
bioprov-0.1.24.dist-info/top_level.txt
bioprov-0.1.24.dist-info/RECORD
